lisflood_utilities-0.6.data/scripts/compare
lisflood_utilities-0.6.data/scripts/cutmaps
lisflood_utilities-0.6.data/scripts/pcr2nc
lisfloodutilities/__init__.py
lisfloodutilities/compare/__init__.py
lisfloodutilities/compare/helpers.py
lisfloodutilities/compare/main.py
lisfloodutilities/cutmaps/__init__.py
lisfloodutilities/cutmaps/cutlib.py
lisfloodutilities/cutmaps/main.py
lisfloodutilities/pcr2nc/__init__.py
lisfloodutilities/pcr2nc/main.py
lisfloodutilities/pcr2nc/reader.py
lisfloodutilities/pcr2nc/writer.py
lisflood_utilities-0.6.dist-info/AUTHORS
lisflood_utilities-0.6.dist-info/LICENSE
lisflood_utilities-0.6.dist-info/METADATA
lisflood_utilities-0.6.dist-info/WHEEL
lisflood_utilities-0.6.dist-info/top_level.txt
lisflood_utilities-0.6.dist-info/zip-safe
lisflood_utilities-0.6.dist-info/RECORD
