Metadata-Version: 2.1
Name: lisflood-utilities
Version: 0.6
Summary: A set of utilities for lisfloodutilities users. pcr2nc: Convert PCRaster files to netCDF; cutmaps: cut netCDF files;compare: to compare two set of netcdf files
Home-page: https://github.com/ec-jrc/lisflood-utilities
Author: Valerio Lorini, Domenico Nappo
Author-email: valerio.lorini@ec.europa.eu,domenico.nappo@gmail.com
License: EUPL 1.2
Keywords: netCDF4,PCRaster,mapstack,lisflood,efas,glofas,ecmwf
Platform: UNKNOWN
Classifier: Development Status :: 4 - Beta
Classifier: Intended Audience :: Developers
Classifier: Intended Audience :: Education
Classifier: Intended Audience :: Other Audience
Classifier: Intended Audience :: Science/Research
Classifier: License :: OSI Approved :: European Union Public Licence 1.2 (EUPL 1.2)
Classifier: Operating System :: Unix
Classifier: Operating System :: POSIX
Classifier: Operating System :: Microsoft :: Windows
Classifier: Operating System :: MacOS :: MacOS X
Classifier: Programming Language :: Python
Classifier: Programming Language :: Python :: 3
Classifier: Topic :: Scientific/Engineering :: Physics
Requires-Dist: numpy (>=1.15)
Requires-Dist: pyyaml
Requires-Dist: netCDF4 (>=1.3.1)
Requires-Dist: xarray
Requires-Dist: dask
Requires-Dist: pandas
